[
  {
    "Book Id": 30962053,
    "Title": "The Idiot",
    "Author": "Elif Batuman",
    "ISBN": "1594205612",
    "ISBN13": 9781594205613,
    "Publisher": "Penguin Press",
    "Binding": "Hardcover",
    "Number of Pages": 423,
    "Year Published": 2017,
    "Original Publication Year": 2017,
    "Date Read": "",
    "Date Added": "8/14/22",
    "Bookshelves": "books-i-love",
    "cover": "30962053.jpg"
  },

  {
    "Book Id": 48616787,
    "Title": "The Lying Life of Adults",
    "Author": "Elena Ferrante",
    "ISBN": "1609455916",
    "ISBN13": 9781609455910,
    "Publisher": "Europa Editions",
    "Binding": "Hardcover",
    "Number of Pages": 336,
    "Year Published": 2020,
    "Original Publication Year": 2019,
    "Date Read": "6/11/23",
    "Date Added": "2/10/23",
    "Bookshelves": "books-i-love",
    "cover": "48616787.jpg"
  },

  {
    "Book Id": 61359016,
    "Title": "The Applicant",
    "Author": "Nazli Koca",
    "ISBN": "802160549",
    "ISBN13": 9780802160546,
    "Publisher": "Grove Press",
    "Binding": "Hardcover",
    "Number of Pages": 304,
    "Year Published": 2023,
    "Original Publication Year": 2023,
    "Date Read": "5/9/23",
    "Date Added": "2/15/23",
    "Bookshelves": "books-i-love",
    "cover": "61359016.jpg"
  },
  {
    "Book Id": 44421460,
    "Title": "Before the Coffee Gets Cold",
    "Author": "Toshikazu Kawaguchi",
    "ISBN": "1529029589",
    "ISBN13": 9781529029581,
    "Publisher": "Picador",
    "Binding": "Paperback",
    "Number of Pages": 213,
    "Year Published": 2019,
    "Original Publication Year": 2015,
    "Date Read": "6/30/23",
    "Date Added": "6/13/23",
    "Bookshelves": "books-i-love",
    "cover": "44421460.jpg"
  },
  {
    "Book Id": 58890783,
    "Title": "Either/Or",
    "Author": "Elif Batuman",
    "ISBN": "525557598",
    "ISBN13": 9780525557593,
    "Publisher": "Penguin Press",
    "Binding": "Hardcover",
    "Number of Pages": 368,
    "Year Published": 2022,
    "Original Publication Year": 2022,
    "Date Read": "8/26/22",
    "Date Added": "6/23/22",
    "Bookshelves": "books-i-love",
    "cover": "58890783.jpg"
  },

  {
    "Book Id": 41057294,
    "Title": "Normal People",
    "Author": "Sally Rooney",
    "ISBN": "1984822179",
    "ISBN13": 9781984822178,
    "Publisher": "Hogarth",
    "Binding": "Hardcover",
    "Number of Pages": 273,
    "Year Published": 2019,
    "Original Publication Year": 2018,
    "Date Read": "1/14/22",
    "Date Added": "12/8/21",
    "Bookshelves": "books-i-love",
    "cover": "41057294.jpg"
  },
  {
    "Book Id": 341879,
    "Title": "Just Kids",
    "Author": "Patti Smith",
    "ISBN": "006621131X",
    "ISBN13": 9780066211312,
    "Publisher": "Ecco",
    "Binding": "Hardcover",
    "Number of Pages": 304,
    "Year Published": 2010,
    "Original Publication Year": 2010,
    "Date Read": "6/13/22",
    "Date Added": "3/30/22",
    "Bookshelves": "books-i-love",
    "cover": "341879.jpg"
  },
  {
    "Book Id": 14935,
    "Title": "Sense and Sensibility",
    "Author": "Jane Austen",
    "ISBN": "",
    "ISBN13": null,
    "Publisher": "Penguin Books",
    "Binding": "Paperback",
    "Number of Pages": 409,
    "Year Published": 2003,
    "Original Publication Year": 1811,
    "Date Read": "8/23/23",
    "Date Added": "8/9/23",
    "Bookshelves": "books-i-love",
    "cover": "14935.jpg"
  },

  {
    "Book Id": 39988,
    "Title": "Matilda",
    "Author": "Roald Dahl",
    "ISBN": "141301066",
    "ISBN13": 9780141301068,
    "Publisher": "Puffin",
    "Binding": "Paperback",
    "Number of Pages": 240,
    "Year Published": 1998,
    "Original Publication Year": 1988,
    "Date Read": "12/20/22",
    "Date Added": "11/20/22",
    "Bookshelves": "books-i-love",
    "cover": "39988.jpg"
  }
]
